rainbowstream/__init__.py
rainbowstream/c_image.py
rainbowstream/colors.py
rainbowstream/config.py
rainbowstream/consumer.py
rainbowstream/draw.py
rainbowstream/emoji.py
rainbowstream/image.c
rainbowstream/interactive.py
rainbowstream/pure_image.py
rainbowstream/py3patch.py
rainbowstream/rainbow.py
rainbowstream/util.py
rainbowstream/colorset/base16.json
rainbowstream/colorset/config
rainbowstream/colorset/larapaste.json
rainbowstream/colorset/monokai.json
rainbowstream/colorset/solarized.json
rainbowstream/colorset/tomorrow_night.json
rainbowstream-1.6.0.dist-info/LICENSE.txt
rainbowstream-1.6.0.dist-info/METADATA
rainbowstream-1.6.0.dist-info/WHEEL
rainbowstream-1.6.0.dist-info/entry_points.txt
rainbowstream-1.6.0.dist-info/top_level.txt
rainbowstream-1.6.0.dist-info/zip-safe
rainbowstream-1.6.0.dist-info/RECORD
