Metadata-Version: 2.1
Name: rainbowstream
Version: 1.6.0
Summary: A smart and nice Twitter client on terminal.
Home-page: http://www.rainbowstream.org/
Author: Vu Nhat Minh
Author-email: nhatminh179@gmail.com
License: MIT License
Keywords: twitter,command-line tools,stream API
Platform: UNKNOWN
Classifier: Development Status :: 5 - Production/Stable
Classifier: Environment :: Console
Classifier: Intended Audience :: End Users/Desktop
Classifier: Natural Language :: English
Classifier: Operating System :: OS Independent
Classifier: Programming Language :: Python :: 2.7
Classifier: Programming Language :: Python :: 3.2
Classifier: Programming Language :: Python :: 3.3
Classifier: Programming Language :: Python :: 3.4
Classifier: Programming Language :: Python :: 3.5
Classifier: Programming Language :: Python :: 3.6
Classifier: Programming Language :: Python :: 3.7
Classifier: Topic :: Internet :: WWW/HTTP :: Dynamic Content :: CGI Tools/Libraries
Classifier: Topic :: Utilities
Classifier: License :: OSI Approved :: MIT License
Requires-Dist: python-dateutil
Requires-Dist: arrow
Requires-Dist: requests
Requires-Dist: pyfiglet
Requires-Dist: twitter
Requires-Dist: Pillow
Requires-Dist: PySocks
Requires-Dist: pocket
Requires-Dist: libsixel-python
Requires-Dist: resize-image
